pygroundsegmentation/__init__.py
pygroundsegmentation/gpf.py
pygroundsegmentation/utils.py
pygroundsegmentation-0.4.2.dist-info/LICENSE
pygroundsegmentation-0.4.2.dist-info/WHEEL
pygroundsegmentation-0.4.2.dist-info/METADATA
pygroundsegmentation-0.4.2.dist-info/RECORD
