Metadata-Version: 2.1
Name: pygroundsegmentation
Version: 0.4.2
Summary: 
Home-page: https://github.com/JonasHablitzel/PyGroundSegmentation
License: MIT
Author: JonasHablitzel
Author-email: Jonas.Hablitzel@gmx.de
Requires-Python: >=3.8,<4.0
Classifier: License :: OSI Approved :: MIT License
Classifier: Programming Language :: Python :: 3
Classifier: Programming Language :: Python :: 3.10
Classifier: Programming Language :: Python :: 3.8
Classifier: Programming Language :: Python :: 3.9
Requires-Dist: numpy (>=1.24.1,<2.0.0)
Project-URL: Repository, https://github.com/JonasHablitzel/PyGroundSegmentation
